skfeaturellm/__init__.py
skfeaturellm/feature_engineer.py
skfeaturellm/feature_evaluation.py
skfeaturellm/llm_interface.py
skfeaturellm/prompts.py
skfeaturellm/reporting.py
skfeaturellm/schemas.py
skfeaturellm/types.py
skfeaturellm-0.0.5.dist-info/LICENSE
skfeaturellm-0.0.5.dist-info/METADATA
skfeaturellm-0.0.5.dist-info/WHEEL
skfeaturellm-0.0.5.dist-info/RECORD
