Metadata-Version: 2.1
Name: skfeaturellm
Version: 0.0.5
Summary: LLM-powered feature engineering with scikit-learn API compatibility
License: MIT
Author: Roberto Corti
Requires-Python: >=3.10,<4.0
Classifier: Development Status :: 3 - Alpha
Classifier: Intended Audience :: Science/Research
Classifier: License :: OSI Approved :: MIT License
Classifier: Programming Language :: Python :: 3
Classifier: Programming Language :: Python :: 3.10
Classifier: Programming Language :: Python :: 3.11
Classifier: Topic :: Scientific/Engineering :: Artificial Intelligence
Provides-Extra: docs
Requires-Dist: langchain-community (>=0.3.20,<0.4.0)
Requires-Dist: langchain-openai (>=0.3.11,<0.4.0)
Requires-Dist: numpy (>=1.20.0,<2.0.0)
Requires-Dist: pandas (>=1.3.0,<2.0.0)
Requires-Dist: pydantic (>=2.0.0,<3.0.0)
Requires-Dist: scikit-learn (>=1.0.0,<2.0.0)
